infisical_python-2.3.6.dist-info/METADATA
infisical_python-2.3.6.dist-info/WHEEL
infisical_python-2.3.6.dist-info/license_files/LICENSE
infisical_client/infisical_client.py
infisical_client/__init__.py
infisical_client/schemas.py
infisical_client/infisical_py.cpython-311-aarch64-linux-gnu.so
infisical_python-2.3.6.dist-info/RECORD
