Metadata-Version: 2.1
Name: infisical-python
Version: 2.3.6
Classifier: Development Status :: 5 - Production/Stable
Classifier: Operating System :: OS Independent
Classifier: Topic :: Software Development :: Libraries :: Application Frameworks
Classifier: Topic :: Software Development :: Libraries :: Python Modules
Classifier: Topic :: Software Development :: Libraries
Classifier: Topic :: Software Development
Classifier: Typing :: Typed
Classifier: Intended Audience :: Developers
Classifier: Programming Language :: Python
Classifier: Programming Language :: Python :: 3.7
Classifier: Programming Language :: Python :: 3.8
Classifier: Programming Language :: Python :: 3.9
Classifier: Programming Language :: Python :: 3.10
Classifier: Programming Language :: Python :: 3.11
Classifier: Programming Language :: Python :: Implementation :: CPython
Classifier: Programming Language :: Python :: Implementation :: PyPy
Classifier: Programming Language :: Python :: Implementation :: CPython
Classifier: Programming Language :: Python :: Implementation :: PyPy
License-File: LICENSE
Summary: Official Infisical SDK for Python (New)
Maintainer-email: Daniel Hougaard <daniel@infisical.com>
Requires-Python: >=3.7
Project-URL: Documentation, https://github.com/Infisical/sdk/tree/main/crates/infisical-py#readme
Project-URL: Source, https://github.com/infisical/sdk
Project-URL: Issues, https://github.com/infisical/sdk/issues
